.DS_Store
scriptlib/__init__.py
scriptlib/scriptfile.py
scriptlib/scriptjson.py
scriptlib/scriptui.py
scriptlib-1.0.3.dist-info/METADATA
scriptlib-1.0.3.dist-info/RECORD
scriptlib-1.0.3.dist-info/WHEEL
scriptlib-1.0.3.dist-info/top_level.txt
