Metadata-Version: 2.1
Name: scriptlib
Version: 1.0.3
Summary: A collection of functions for easy terminal application development
Home-page: https://github.com/Orbtial/scriptlib
Author: Orbtial
Author-email: thewardloch@gmail.com
License: MIT
Platform: UNKNOWN
Classifier: Programming Language :: Python :: 3
Classifier: License :: OSI Approved :: MIT License
Classifier: Operating System :: MacOS :: MacOS X
